nxfern2/__init__.py
nxfern2/first.py
nxfern2-1.3.dist-info/METADATA
nxfern2-1.3.dist-info/WHEEL
nxfern2-1.3.dist-info/top_level.txt
nxfern2-1.3.dist-info/RECORD
