Metadata-Version: 2.1
Name: nxfern2
Version: 1.3
Summary: Demo package
Home-page: 
Author: Nicolas Fernandez
Author-email: 
License: MIT
